balisage/__init__.py
balisage/attributes.py
balisage/core.py
balisage/types.py
balisage/elements/__init__.py
balisage/elements/basic.py
balisage/elements/format.py
balisage/elements/image.py
balisage/elements/links.py
balisage/elements/lists.py
balisage/elements/styles.py
balisage/elements/tables.py
balisage/elements/text.py
balisage/utilities/__init__.py
balisage/utilities/optional.py
balisage/utilities/validate.py
balisage-0.4.5.dist-info/METADATA
balisage-0.4.5.dist-info/WHEEL
balisage-0.4.5.dist-info/top_level.txt
balisage-0.4.5.dist-info/RECORD
