Metadata-Version: 2.2
Name: balisage
Version: 0.4.5
Summary: Generate HTML using an intuitive Python interface.
Requires-Python: >=3.11
Provides-Extra: data
Requires-Dist: pandas>=2.2.3; extra == "data"
Provides-Extra: formatting
Requires-Dist: beautifulsoup4>=4.13.3; extra == "formatting"
